shitsort/__init__.py
shitsort/bogo.py
shitsort/bozo.py
shitsort/multibogo.py
shitsort/multipermutation.py
shitsort/peripherals.py
shitsort/permutation.py
shitsort/slow.py
shitsort/slowsort.py
shitsort-1.2.0.dist-info/LICENSE.txt
shitsort-1.2.0.dist-info/METADATA
shitsort-1.2.0.dist-info/WHEEL
shitsort-1.2.0.dist-info/top_level.txt
shitsort-1.2.0.dist-info/RECORD
