Metadata-Version: 2.1
Name: shitsort
Version: 1.2.0
Summary: Really really bad sorting algorithms
Home-page: https://github.com/sh6heer/shitty-sorting-algorithms
Author: sh6heer
Author-email: 
License: GNU GPLv3
Platform: UNKNOWN
Classifier: Programming Language :: Python :: 3
Classifier: Programming Language :: Python :: 3.9
License-File: LICENSE.txt
